bartste_prompts-1.3.1.dist-info/licenses/LICENSE
prompts/__init__.py
prompts/__main__.py
prompts/_logger.py
prompts/_parser.py
prompts/_paths.py
prompts/actions.py
prompts/exceptions.py
prompts/instructions.py
prompts/py.typed
prompts/_instructions/commands/ask/command.md
prompts/_instructions/commands/commit/command.md
prompts/_instructions/commands/commit/user.md
prompts/_instructions/commands/docstrings/command.md
prompts/_instructions/commands/docstrings/files.md
prompts/_instructions/commands/docstrings/filetype/bash.md
prompts/_instructions/commands/docstrings/filetype/c.md
prompts/_instructions/commands/docstrings/filetype/cpp.md
prompts/_instructions/commands/docstrings/filetype/lua.md
prompts/_instructions/commands/docstrings/filetype/python.md
prompts/_instructions/commands/docstrings/filetype/zsh.md
prompts/_instructions/commands/explain/command.md
prompts/_instructions/commands/fix/command.md
prompts/_instructions/commands/fix/filetype/python.md
prompts/_instructions/commands/refactor/command.md
prompts/_instructions/commands/refactor/filetype/python.md
prompts/_instructions/commands/typehints/command.md
prompts/_instructions/commands/typehints/filetype/python.md
prompts/_instructions/commands/unittests/command.md
prompts/_instructions/commands/unittests/filetype/python.md
prompts/_instructions/default/files.md
prompts/_instructions/default/user.md
prompts/_instructions/default/filetype/bash.md
prompts/_instructions/default/filetype/c.md
prompts/_instructions/default/filetype/cpp.md
prompts/_instructions/default/filetype/lua.md
prompts/_instructions/default/filetype/python.md
prompts/_instructions/default/filetype/yaml.md
prompts/_instructions/default/filetype/zsh.md
bartste_prompts-1.3.1.dist-info/METADATA
bartste_prompts-1.3.1.dist-info/WHEEL
bartste_prompts-1.3.1.dist-info/entry_points.txt
bartste_prompts-1.3.1.dist-info/top_level.txt
bartste_prompts-1.3.1.dist-info/RECORD
