Metadata-Version: 2.4
Name: bartste-prompts
Version: 1.3.1
Summary: A collection of prompts
Author: BartSte
License: MIT
Requires-Python: >=3.10
License-File: LICENSE
Requires-Dist: pygeneral~=0.2
Provides-Extra: dev
Requires-Dist: pre-commit>=3.0.0; extra == "dev"
Requires-Dist: pytest>=7.0.0; extra == "dev"
Requires-Dist: ipdb; extra == "dev"
Requires-Dist: ipython; extra == "dev"
Dynamic: license-file
